odoo/addons/mobile_app_picking/README.rst
odoo/addons/mobile_app_picking/__init__.py
odoo/addons/mobile_app_picking/__manifest__.py
odoo/addons/mobile_app_picking/controllers/__init__.py
odoo/addons/mobile_app_picking/controllers/main.py
odoo/addons/mobile_app_picking/demo/stock_picking.xml
odoo/addons/mobile_app_picking/demo/stock_picking_type.xml
odoo/addons/mobile_app_picking/i18n/fr.po
odoo/addons/mobile_app_picking/i18n/mobile_app_picking.pot
odoo/addons/mobile_app_picking/models/__init__.py
odoo/addons/mobile_app_picking/models/mobile_app_picking.py
odoo/addons/mobile_app_picking/models/stock_picking.py
odoo/addons/mobile_app_picking/models/stock_picking_type.py
odoo/addons/mobile_app_picking/readme/CONFIGURE.rst
odoo/addons/mobile_app_picking/readme/CONTRIBUTORS.rst
odoo/addons/mobile_app_picking/readme/CREDITS.rst
odoo/addons/mobile_app_picking/readme/DESCRIPTION.rst
odoo/addons/mobile_app_picking/readme/ROADMAP.rst
odoo/addons/mobile_app_picking/readme/USAGE.rst
odoo/addons/mobile_app_picking/security/ir.model.access.csv
odoo/addons/mobile_app_picking/static/description/icon.png
odoo/addons/mobile_app_picking/static/description/index.html
odoo/addons/mobile_app_picking/static/description/mobile_01_authentication.png
odoo/addons/mobile_app_picking/static/description/mobile_02_list_picking_type.png
odoo/addons/mobile_app_picking/static/description/mobile_03_list_picking.png
odoo/addons/mobile_app_picking/static/description/mobile_04_list_move.png
odoo/addons/mobile_app_picking/static/description/mobile_05_scan_mode.png
odoo/addons/mobile_app_picking/static/description/mobile_06_list_move_change.png
odoo/addons/mobile_app_picking/static/description/mobile_07_picking_confirmation.png
odoo/addons/mobile_app_picking/static/description/stock_picking_type_form.png
odoo/addons/mobile_app_picking/static/www/app.js
odoo/addons/mobile_app_picking/static/www/index.html
odoo/addons/mobile_app_picking/static/www/controllers/credit.js
odoo11_addon_mobile_app_picking-11.0.1.0.0.99.dev13.dist-info/METADATA
odoo11_addon_mobile_app_picking-11.0.1.0.0.99.dev13.dist-info/WHEEL
odoo11_addon_mobile_app_picking-11.0.1.0.0.99.dev13.dist-info/top_level.txt
odoo11_addon_mobile_app_picking-11.0.1.0.0.99.dev13.dist-info/RECORD
